utils4ymc/__init__.py
utils4ymc/Decos/__init__.py
utils4ymc/Decos/check_args.py
utils4ymc/Decos/decorators.py
utils4ymc/Tools/__init__.py
utils4ymc/Tools/calculate.py
utils4ymc/Tools/file.py
utils4ymc-0.1.2.dist-info/LICENSE
utils4ymc-0.1.2.dist-info/METADATA
utils4ymc-0.1.2.dist-info/WHEEL
utils4ymc-0.1.2.dist-info/top_level.txt
utils4ymc-0.1.2.dist-info/RECORD
