Metadata-Version: 2.1
Name: utils4ymc
Version: 0.1.2
Summary: Making our programing more efficient.
Home-page: https://github.com/interesting6/utils4ymc
Author: Yummy Chen
Author-email: chenymcan@gmail.com
License: UNKNOWN
Platform: UNKNOWN
Classifier: Programming Language :: Python :: 3
Classifier: License :: OSI Approved :: MIT License
Classifier: Operating System :: OS Independent
Requires-Python: >=3.6
Requires-Dist: numpy (>=1.15)
